magento/__init__.py
magento/attributes.py
magento/batches.py
magento/client.py
magento/dates.py
magento/exceptions.py
magento/order_helpers.py
magento/py.typed
magento/queries.py
magento/types.py
magento/version.py
pymagento-2.12.1.dist-info/METADATA
pymagento-2.12.1.dist-info/WHEEL
pymagento-2.12.1.dist-info/licenses/LICENSE
pymagento-2.12.1.dist-info/RECORD
