Metadata-Version: 2.4
Name: pymagento
Version: 2.12.1
Summary: Python client for the Magento 2 API
License: MIT
License-File: LICENSE
Keywords: magento,magento-api,python-magento,magento-python,pymagento,py-magento,magento-rest-api,magento2,magento-2,magento2-api,magento2-rest-api
Author: Bixoto
Author-email: tech@bixoto.com
Requires-Python: >=3.9,<4.0
Classifier: Development Status :: 5 - Production/Stable
Classifier: License :: OSI Approved :: MIT License
Classifier: Programming Language :: Python :: 3
Classifier: Programming Language :: Python :: 3.9
Classifier: Programming Language :: Python :: 3.10
Classifier: Programming Language :: Python :: 3.11
Classifier: Programming Language :: Python :: 3.12
Classifier: Programming Language :: Python :: 3.13
Classifier: Programming Language :: Python :: 3.14
Provides-Extra: docs
Requires-Dist: Sphinx (>=5.0,<6.0) ; extra == "docs"
Requires-Dist: api-session (>=1.5.2,<2.0.0)
Requires-Dist: sphinx-rtd-theme (>=2.0,<3.0) ; extra == "docs"
Requires-Dist: typing-extensions ; python_version < "3.11"
Project-URL: Homepage, https://github.com/Bixoto/PyMagento
